setup.py
django_url_utils.egg-info/PKG-INFO
django_url_utils.egg-info/SOURCES.txt
django_url_utils.egg-info/dependency_links.txt
django_url_utils.egg-info/requires.txt
django_url_utils.egg-info/top_level.txt
url_utils/__init__.py
url_utils/models.py
url_utils/tests.py
url_utils/templatetags/__init__.py
url_utils/templatetags/url_utils.py