Metadata-Version: 1.0
Name: django-url-utils
Version: 1.0.0
Summary: Django template tags for manipulating URLs
Home-page: http://github.com/brightinteractive/django-url-utils/
Author: Bright Interactive
Author-email: francis@bright-interactive.co.uk
License: BSD
Platform: UNKNOWN
